hubstudio_api/__init__.py
hubstudio_api/hubstudio_api.py
hubstudio_api-0.1.dist-info/LICENSE
hubstudio_api-0.1.dist-info/METADATA
hubstudio_api-0.1.dist-info/WHEEL
hubstudio_api-0.1.dist-info/top_level.txt
hubstudio_api-0.1.dist-info/RECORD
